<?xml version="1.0" encoding="UTF-8" ?>
<bmtactionlog project="D:\My Documents\My Source\Cognos Projects\sghe_ods_bv\sghe_ods_bv.cpf" templatedir="../templates/bmt/Cr1Model" timestamp="20070518111350055" user="dawilson" version="2.0.1886.0"><transaction saved="true" seq="1" timestamp="20070518111456727"><action seq="1" type="SetActiveLocale"><inputparams><param seq="1" type="i18nstring"><value>en</value></param></inputparams><domchanges/><result success="t"><outputparams/></result></action></transaction><transaction saved="true" seq="2" timestamp="20070518111812649"><action seq="1" type="SetSecurityViewDefinition"><inputparams><param seq="1" type="handle"><mappingpath>securityView</mappingpath><value>[].[securityViews].[Active Registration]</value></param><param seq="2" type="handle"><mappingpath>namespace</mappingpath><value>[Active Registration]</value></param><param seq="3" type="integer"><value>2</value></param><param seq="4" type="handle"><mappingpath>namespace</mappingpath><value>[Person Supplemental]</value></param><param seq="5" type="integer"><value>2</value></param><param seq="6" type="handle"><mappingpath>namespace</mappingpath><value>[List of Values]</value></param><param seq="7" type="integer"><value>2</value></param></inputparams><domchanges/><result success="t"><outputparams/></result></action></transaction><transaction saved="true" seq="3" timestamp="20070518111947524"><action seq="1" type="SetSecurityViewDefinition"><inputparams><param seq="1" type="handle"><mappingpath>securityView</mappingpath><value>[].[securityViews].[Admissions Application]</value></param><param seq="2" type="handle"><mappingpath>namespace</mappingpath><value>[Admission Application]</value></param><param seq="3" type="integer"><value>2</value></param><param seq="4" type="handle"><mappingpath>namespace</mappingpath><value>[Person Supplemental]</value></param><param seq="5" type="integer"><value>2</value></param><param seq="6" type="handle"><mappingpath>namespace</mappingpath><value>[List of Values]</value></param><param seq="7" type="integer"><value>2</value></param></inputparams><domchanges/><result success="t"><outputparams/></result></action></transaction><transaction saved="true" seq="4" timestamp="20070518113222555"><action seq="1" type="SetSecurityViewDefinition"><inputparams><param seq="1" type="handle"><mappingpath>securityView</mappingpath><value>[].[securityViews].[Advancement Prospect]</value></param><param seq="2" type="handle"><mappingpath>namespace</mappingpath><value>[Advancement Prospect]</value></param><param seq="3" type="integer"><value>2</value></param><param seq="4" type="handle"><mappingpath>namespace</mappingpath><value>[Person Supplemental]</value></param><param seq="5" type="integer"><value>2</value></param><param seq="6" type="handle"><mappingpath>namespace</mappingpath><value>[List of Values]</value></param><param seq="7" type="integer"><value>2</value></param></inputparams><domchanges/><result success="t"><outputparams/></result></action></transaction><transaction saved="true" seq="5" timestamp="20070518113405727"><action seq="1" type="SetSecurityViewDefinition"><inputparams><param seq="1" type="handle"><mappingpath>securityView</mappingpath><value>[].[securityViews].[Advancement Rating]</value></param><param seq="2" type="handle"><mappingpath>namespace</mappingpath><value>[Advancement Rating]</value></param><param seq="3" type="integer"><value>2</value></param><param seq="4" type="handle"><mappingpath>namespace</mappingpath><value>[Person Supplemental]</value></param><param seq="5" type="integer"><value>2</value></param><param seq="6" type="handle"><mappingpath>namespace</mappingpath><value>[List of Values]</value></param><param seq="7" type="integer"><value>2</value></param></inputparams><domchanges/><result success="t"><outputparams/></result></action></transaction><transaction saved="true" seq="6" timestamp="20070518113446555"><action seq="1" type="SetSecurityViewDefinition"><inputparams><param seq="1" type="handle"><mappingpath>securityView</mappingpath><value>[].[securityViews].[Advisor Student List]</value></param><param seq="2" type="handle"><mappingpath>namespace</mappingpath><value>[Advisor Student List]</value></param><param seq="3" type="integer"><value>2</value></param><param seq="4" type="handle"><mappingpath>namespace</mappingpath><value>[Person Supplemental]</value></param><param seq="5" type="integer"><value>2</value></param><param seq="6" type="handle"><mappingpath>namespace</mappingpath><value>[List of Values]</value></param><param seq="7" type="integer"><value>2</value></param></inputparams><domchanges/><result success="t"><outputparams/></result></action></transaction><transaction saved="true" seq="7" timestamp="20070518113943696"><action seq="1" type="SetSecurityViewDefinition"><inputparams><param seq="1" type="handle"><mappingpath>securityView</mappingpath><value>[].[securityViews].[Annual Giving]</value></param><param seq="2" type="handle"><mappingpath>namespace</mappingpath><value>[Annual Giving]</value></param><param seq="3" type="integer"><value>2</value></param><param seq="4" type="handle"><mappingpath>namespace</mappingpath><value>[Person Supplemental]</value></param><param seq="5" type="integer"><value>2</value></param><param seq="6" type="handle"><mappingpath>namespace</mappingpath><value>[List of Values]</value></param><param seq="7" type="integer"><value>2</value></param></inputparams><domchanges/><result success="t"><outputparams/></result></action></transaction><transaction saved="true" seq="8" timestamp="20070518114222821"><action seq="1" type="SetSecurityViewDefinition"><inputparams><param seq="1" type="handle"><mappingpath>securityView</mappingpath><value>[].[securityViews].[Budget Availability Ledger]</value></param><param seq="2" type="handle"><mappingpath>namespace</mappingpath><value>[Budget Availability Ledger]</value></param><param seq="3" type="integer"><value>2</value></param><param seq="4" type="handle"><mappingpath>namespace</mappingpath><value>[List of Values]</value></param><param seq="5" type="integer"><value>2</value></param></inputparams><domchanges/><result success="t"><outputparams/></result></action></transaction><transaction saved="true" seq="9" timestamp="20070518114321165"><action seq="1" type="SetSecurityViewDefinition"><inputparams><param seq="1" type="handle"><mappingpath>securityView</mappingpath><value>[].[securityViews].[Budget Detail]</value></param><param seq="2" type="handle"><mappingpath>namespace</mappingpath><value>[Budget Detail]</value></param><param seq="3" type="integer"><value>2</value></param><param seq="4" type="handle"><mappingpath>namespace</mappingpath><value>[List of Values]</value></param><param seq="5" type="integer"><value>2</value></param></inputparams><domchanges/><result success="t"><outputparams/></result></action></transaction><transaction saved="true" seq="10" timestamp="20070518114404102"><action seq="1" type="SetSecurityViewDefinition"><inputparams><param seq="1" type="handle"><mappingpath>securityView</mappingpath><value>[].[securityViews].[Campaign Giving History]</value></param><param seq="2" type="handle"><mappingpath>namespace</mappingpath><value>[Campaign Giving History]</value></param><param seq="3" type="integer"><value>2</value></param><param seq="4" type="handle"><mappingpath>namespace</mappingpath><value>[Person Supplemental]</value></param><param seq="5" type="integer"><value>2</value></param><param seq="6" type="handle"><mappingpath>namespace</mappingpath><value>[List of Values]</value></param><param seq="7" type="integer"><value>2</value></param></inputparams><domchanges/><result success="t"><outputparams/></result></action></transaction><transaction saved="true" seq="11" timestamp="20070518114524961"><action seq="1" type="SetSecurityViewDefinition"><inputparams><param seq="1" type="handle"><mappingpath>securityView</mappingpath><value>[].[securityViews].[Constituent]</value></param><param seq="2" type="handle"><mappingpath>namespace</mappingpath><value>[Constituent]</value></param><param seq="3" type="integer"><value>2</value></param><param seq="4" type="handle"><mappingpath>namespace</mappingpath><value>[Person Supplemental]</value></param><param seq="5" type="integer"><value>2</value></param><param seq="6" type="handle"><mappingpath>namespace</mappingpath><value>[List of Values]</value></param><param seq="7" type="integer"><value>2</value></param></inputparams><domchanges/><result success="t"><outputparams/></result></action></transaction><transaction saved="true" seq="12" timestamp="20070518114626618"><action seq="1" type="SetSecurityViewDefinition"><inputparams><param seq="1" type="handle"><mappingpath>securityView</mappingpath><value>[].[securityViews].[Constituent Entity]</value></param><param seq="2" type="handle"><mappingpath>namespace</mappingpath><value>[Constituent Entity]</value></param><param seq="3" type="integer"><value>2</value></param><param seq="4" type="handle"><mappingpath>namespace</mappingpath><value>[List of Values]</value></param><param seq="5" type="integer"><value>2</value></param></inputparams><domchanges/><result success="t"><outputparams/></result></action></transaction><transaction saved="true" seq="13" timestamp="20070518114846290"><action seq="1" type="SetSecurityViewDefinition"><inputparams><param seq="1" type="handle"><mappingpath>securityView</mappingpath><value>[].[securityViews].[Course Catalog]</value></param><param seq="2" type="handle"><mappingpath>namespace</mappingpath><value>[Course Catalog]</value></param><param seq="3" type="integer"><value>2</value></param><param seq="4" type="handle"><mappingpath>namespace</mappingpath><value>[List of Values]</value></param><param seq="5" type="integer"><value>2</value></param></inputparams><domchanges/><result success="t"><outputparams/></result></action></transaction><transaction saved="true" seq="14" timestamp="20070518115601352"/></bmtactionlog>
